convertor/__init__.py
convertor/convertor.py
iotedge_compose-0.1.2.dist-info/LICENSE
iotedge_compose-0.1.2.dist-info/METADATA
iotedge_compose-0.1.2.dist-info/WHEEL
iotedge_compose-0.1.2.dist-info/entry_points.txt
iotedge_compose-0.1.2.dist-info/top_level.txt
iotedge_compose-0.1.2.dist-info/RECORD
