Metadata-Version: 2.1
Name: iotedge-compose
Version: 0.1.2
Summary: Convert Docker Compose project to Azure IoT Edge deployment manifest
Home-page: https://github.com/VSChina/compose-to-manifest
Author: iotedge
Author-email: vsciet@outlook.com
License: UNKNOWN
Platform: UNKNOWN
Classifier: Programming Language :: Python :: 3
Requires-Python: >=3.6.0
Requires-Dist: docker-compose (==1.24.0)
